[{"exception": "org.eclipse.emf.cdo.util.CommitException", "inner": [{"provider": {"package": "org.eclipse.ui.internal", "class": "WorkbenchWindow$14", "method": "run", "filename": "WorkbenchWindow", "line": "2181"}, "caller": {"package": "org.eclipse.swt.custom", "class": "BusyIndicator", "method": "showWhile", "filename": "BusyIndicator", "line": "70"}}, {"provider": {"package": "org.eclipse.swt.custom", "class": "BusyIndicator", "method": "showWhile", "filename": "BusyIndicator", "line": "70"}, "caller": {"package": "org.eclipse.ui.internal", "class": "WorkbenchWindow", "method": "run", "filename": "WorkbenchWindow", "line": "2177"}}, {"provider": {"package": "org.eclipse.ui.internal", "class": "WorkbenchPage", "method": "saveAllEditors", "filename": "WorkbenchPage", "line": "3638"}, "caller": {"package": "org.eclipse.ui.internal.handlers", "class": "SaveAllHandler", "method": "execute", "filename": "SaveAllHandler", "line": "48"}}, {"provider": {"package": "org.eclipse.ui.internal.handlers", "class": "E4HandlerProxy", "method": "execute", "filename": "E4HandlerProxy", "line": "90"}, "caller": {"package": "sun.reflect", "class": "NativeMethodAccessorImpl", "method": "invoke0", "filename": "NativeMethodAccessorImpl", "line": "-2"}}], "outer_pre": [{"provider": {"package": "org.eclipse.emf.cdo.eresource.impl", "class": "CDOResourceImpl", "method": "save", "filename": "CDOResourceImpl", "line": "1336"}, "caller": {"package": "org.eclipse.papyrus.infra.core.resource", "class": "EMFLogicalModel", "method": "saveModel", "filename": "EMFLogicalModel", "line": "80"}}, {"provider": {"package": "org.eclipse.papyrus.infra.core.resource", "class": "ModelSet", "method": "save", "filename": "ModelSet", "line": "773"}, "caller": {"package": "org.eclipse.papyrus.cdo.core.resource", "class": "CDOAwareModelSet", "method": "save", "filename": "CDOAwareModelSet", "line": "422"}}, {"provider": {"package": "org.eclipse.papyrus.cdo.core.resource", "class": "CDOAwareModelSet", "method": "save", "filename": "CDOAwareModelSet", "line": "422"}, "caller": {"package": "org.eclipse.papyrus.infra.core.lifecycleevents", "class": "SaveAndDirtyService", "method": "doSave", "filename": "SaveAndDirtyService", "line": "286"}}, {"provider": {"package": "org.eclipse.papyrus.infra.core.lifecycleevents", "class": "SaveAndDirtyService", "method": "doSave", "filename": "SaveAndDirtyService", "line": "286"}, "caller": {"package": "org.eclipse.papyrus.infra.core.editor", "class": "CoreMultiDiagramEditor", "method": "doSave", "filename": "CoreMultiDiagramEditor", "line": "980"}}, {"provider": {"package": "org.eclipse.papyrus.infra.core.editor", "class": "CoreMultiDiagramEditor", "method": "doSave", "filename": "CoreMultiDiagramEditor", "line": "980"}, "caller": {"package": "org.eclipse.ui.internal", "class": "DefaultSaveable", "method": "doSave", "filename": "DefaultSaveable", "line": "51"}}, {"provider": {"package": "org.eclipse.ui.internal", "class": "DefaultSaveable", "method": "doSave", "filename": "DefaultSaveable", "line": "51"}, "caller": {"package": "org.eclipse.ui", "class": "Saveable", "method": "doSave", "filename": "Saveable", "line": "216"}}, {"provider": {"package": "org.eclipse.ui", "class": "Saveable", "method": "doSave", "filename": "Saveable", "line": "216"}, "caller": {"package": "org.eclipse.ui.internal", "class": "SaveableHelper", "method": "doSaveModel", "filename": "SaveableHelper", "line": "357"}}, {"provider": {"package": "org.eclipse.ui.internal", "class": "SaveableHelper$5", "method": "run", "filename": "SaveableHelper", "line": "285"}, "caller": {"package": "org.eclipse.jface.operation", "class": "ModalContext", "method": "runInCurrentThread", "filename": "ModalContext", "line": "463"}}, {"provider": {"package": "org.eclipse.jface.operation", "class": "ModalContext", "method": "run", "filename": "ModalContext", "line": "371"}, "caller": {"package": "org.eclipse.ui.internal", "class": "WorkbenchWindow$14", "method": "run", "filename": "WorkbenchWindow", "line": "2181"}}, {"provider": {"package": "org.eclipse.ui.internal", "class": "WorkbenchWindow$14", "method": "run", "filename": "WorkbenchWindow", "line": "2181"}, "caller": {"package": "org.eclipse.swt.custom", "class": "BusyIndicator", "method": "showWhile", "filename": "BusyIndicator", "line": "70"}}, {"provider": {"package": "org.eclipse.swt.custom", "class": "BusyIndicator", "method": "showWhile", "filename": "BusyIndicator", "line": "70"}, "caller": {"package": "org.eclipse.ui.internal", "class": "WorkbenchWindow", "method": "run", "filename": "WorkbenchWindow", "line": "2177"}}], "outer_suf": [], "all": [{"provider": {"package": "org.eclipse.emf.cdo.eresource.impl", "class": "CDOResourceImpl", "method": "save", "filename": "CDOResourceImpl", "line": "1336"}, "caller": {"package": "org.eclipse.papyrus.infra.core.resource", "class": "EMFLogicalModel", "method": "saveModel", "filename": "EMFLogicalModel", "line": "80"}}]}, {"exception": "org.eclipse.emf.cdo.util.CommitException", "inner": [{"provider": {"package": "org.eclipse.ui.internal", "class": "WorkbenchWindow$14", "method": "run", "filename": "WorkbenchWindow", "line": "2181"}, "caller": {"package": "org.eclipse.swt.custom", "class": "BusyIndicator", "method": "showWhile", "filename": "BusyIndicator", "line": "70"}}, {"provider": {"package": "org.eclipse.swt.custom", "class": "BusyIndicator", "method": "showWhile", "filename": "BusyIndicator", "line": "70"}, "caller": {"package": "org.eclipse.ui.internal", "class": "WorkbenchWindow", "method": "run", "filename": "WorkbenchWindow", "line": "2177"}}, {"provider": {"package": "org.eclipse.ui.internal", "class": "WorkbenchPage", "method": "saveAllEditors", "filename": "WorkbenchPage", "line": "3638"}, "caller": {"package": "org.eclipse.ui.internal.handlers", "class": "SaveAllHandler", "method": "execute", "filename": "SaveAllHandler", "line": "48"}}, {"provider": {"package": "org.eclipse.ui.internal.handlers", "class": "E4HandlerProxy", "method": "execute", "filename": "E4HandlerProxy", "line": "90"}, "caller": {"package": "sun.reflect", "class": "NativeMethodAccessorImpl", "method": "invoke0", "filename": "NativeMethodAccessorImpl", "line": "-2"}}], "outer_pre": [{"provider": {"package": "org.eclipse.emf.internal.cdo.transaction", "class": "CDOTransactionImpl", "method": "commit", "filename": "CDOTransactionImpl", "line": "1290"}, "caller": {"package": "org.eclipse.emf.cdo.eresource.impl", "class": "CDOResourceImpl", "method": "save", "filename": "CDOResourceImpl", "line": "1332"}}, {"provider": {"package": "org.eclipse.emf.cdo.eresource.impl", "class": "CDOResourceImpl", "method": "save", "filename": "CDOResourceImpl", "line": "1332"}, "caller": {"package": "org.eclipse.papyrus.infra.core.resource", "class": "EMFLogicalModel", "method": "saveModel", "filename": "EMFLogicalModel", "line": "80"}}, {"provider": {"package": "org.eclipse.papyrus.infra.core.resource", "class": "ModelSet", "method": "save", "filename": "ModelSet", "line": "773"}, "caller": {"package": "org.eclipse.papyrus.cdo.core.resource", "class": "CDOAwareModelSet", "method": "save", "filename": "CDOAwareModelSet", "line": "422"}}, {"provider": {"package": "org.eclipse.papyrus.cdo.core.resource", "class": "CDOAwareModelSet", "method": "save", "filename": "CDOAwareModelSet", "line": "422"}, "caller": {"package": "org.eclipse.papyrus.infra.core.lifecycleevents", "class": "SaveAndDirtyService", "method": "doSave", "filename": "SaveAndDirtyService", "line": "286"}}, {"provider": {"package": "org.eclipse.papyrus.infra.core.lifecycleevents", "class": "SaveAndDirtyService", "method": "doSave", "filename": "SaveAndDirtyService", "line": "286"}, "caller": {"package": "org.eclipse.papyrus.infra.core.editor", "class": "CoreMultiDiagramEditor", "method": "doSave", "filename": "CoreMultiDiagramEditor", "line": "980"}}, {"provider": {"package": "org.eclipse.papyrus.infra.core.editor", "class": "CoreMultiDiagramEditor", "method": "doSave", "filename": "CoreMultiDiagramEditor", "line": "980"}, "caller": {"package": "org.eclipse.ui.internal", "class": "DefaultSaveable", "method": "doSave", "filename": "DefaultSaveable", "line": "51"}}, {"provider": {"package": "org.eclipse.ui.internal", "class": "DefaultSaveable", "method": "doSave", "filename": "DefaultSaveable", "line": "51"}, "caller": {"package": "org.eclipse.ui", "class": "Saveable", "method": "doSave", "filename": "Saveable", "line": "216"}}, {"provider": {"package": "org.eclipse.ui", "class": "Saveable", "method": "doSave", "filename": "Saveable", "line": "216"}, "caller": {"package": "org.eclipse.ui.internal", "class": "SaveableHelper", "method": "doSaveModel", "filename": "SaveableHelper", "line": "357"}}, {"provider": {"package": "org.eclipse.ui.internal", "class": "SaveableHelper$5", "method": "run", "filename": "SaveableHelper", "line": "285"}, "caller": {"package": "org.eclipse.jface.operation", "class": "ModalContext", "method": "runInCurrentThread", "filename": "ModalContext", "line": "463"}}, {"provider": {"package": "org.eclipse.jface.operation", "class": "ModalContext", "method": "run", "filename": "ModalContext", "line": "371"}, "caller": {"package": "org.eclipse.ui.internal", "class": "WorkbenchWindow$14", "method": "run", "filename": "WorkbenchWindow", "line": "2181"}}, {"provider": {"package": "org.eclipse.ui.internal", "class": "WorkbenchWindow$14", "method": "run", "filename": "WorkbenchWindow", "line": "2181"}, "caller": {"package": "org.eclipse.swt.custom", "class": "BusyIndicator", "method": "showWhile", "filename": "BusyIndicator", "line": "70"}}, {"provider": {"package": "org.eclipse.swt.custom", "class": "BusyIndicator", "method": "showWhile", "filename": "BusyIndicator", "line": "70"}, "caller": {"package": "org.eclipse.ui.internal", "class": "WorkbenchWindow", "method": "run", "filename": "WorkbenchWindow", "line": "2177"}}], "outer_suf": [], "all": [{"provider": {"package": "org.eclipse.emf.internal.cdo.transaction", "class": "CDOTransactionImpl", "method": "commit", "filename": "CDOTransactionImpl", "line": "1290"}, "caller": {"package": "org.eclipse.emf.cdo.eresource.impl", "class": "CDOResourceImpl", "method": "save", "filename": "CDOResourceImpl", "line": "1332"}}]}, {"exception": "java.lang.IllegalStateException", "inner": [{"provider": {"package": "org.eclipse.emf.cdo.internal.net4j.protocol", "class": "CDOClientRequestWithMonitoring", "method": "requesting", "filename": "CDOClientRequestWithMonitoring", "line": "92"}, "caller": {"package": "org.eclipse.net4j.signal", "class": "RequestWithMonitoring", "method": "requesting", "filename": "RequestWithMonitoring", "line": "168"}}, {"provider": {"package": "org.eclipse.net4j.signal", "class": "RequestWithMonitoring", "method": "send", "filename": "RequestWithMonitoring", "line": "106"}, "caller": {"package": "org.eclipse.emf.cdo.internal.net4j.protocol", "class": "CDOClientProtocol", "method": "send", "filename": "CDOClientProtocol", "line": "573"}}], "outer_pre": [{"provider": {"package": "org.eclipse.emf.cdo.common.model", "class": "CDOModelUtil", "method": "writePackage", "filename": "CDOModelUtil", "line": "630"}, "caller": {"package": "org.eclipse.emf.cdo.internal.common.model", "class": "CDOPackageUnitImpl", "method": "write", "filename": "CDOPackageUnitImpl", "line": "270"}}, {"provider": {"package": "org.eclipse.emf.cdo.internal.common.model", "class": "CDOPackageUnitImpl", "method": "write", "filename": "CDOPackageUnitImpl", "line": "270"}, "caller": {"package": "org.eclipse.emf.cdo.spi.common.protocol", "class": "CDODataOutputImpl", "method": "writeCDOPackageUnit", "filename": "CDODataOutputImpl", "line": "92"}}, {"provider": {"package": "org.eclipse.emf.cdo.spi.common.protocol", "class": "CDODataOutputImpl", "method": "writeCDOPackageUnit", "filename": "CDODataOutputImpl", "line": "92"}, "caller": {"package": "org.eclipse.emf.cdo.internal.net4j.protocol", "class": "CommitTransactionRequest", "method": "requestingCommit", "filename": "CommitTransactionRequest", "line": "159"}}, {"provider": {"package": "org.eclipse.emf.cdo.internal.net4j.protocol", "class": "CDOClientRequestWithMonitoring", "method": "requesting", "filename": "CDOClientRequestWithMonitoring", "line": "92"}, "caller": {"package": "org.eclipse.net4j.signal", "class": "RequestWithMonitoring", "method": "requesting", "filename": "RequestWithMonitoring", "line": "168"}}], "outer_suf": [], "all": [{"provider": {"package": "org.eclipse.emf.cdo.common.model", "class": "CDOModelUtil", "method": "writePackage", "filename": "CDOModelUtil", "line": "630"}, "caller": {"package": "org.eclipse.emf.cdo.internal.common.model", "class": "CDOPackageUnitImpl", "method": "write", "filename": "CDOPackageUnitImpl", "line": "270"}}]}]