[{"exception": "javax.servlet.ServletException", "inner": [{"provider": {"package": "org.aspectj.weaver.bcel", "class": "BcelShadow", "method": "prepareForMungers", "filename": "BcelShadow", "line": "284"}, "caller": {"package": "org.aspectj.weaver", "class": "Shadow", "method": "implement", "filename": "Shadow", "line": "470"}}, {"provider": {"package": "org.aspectj.weaver", "class": "Shadow", "method": "implement", "filename": "Shadow", "line": "470"}, "caller": {"package": "org.aspectj.weaver.bcel", "class": "BcelClassWeaver", "method": "implement", "filename": "BcelClassWeaver", "line": "2825"}}, {"provider": {"package": "org.aspectj.weaver.bcel", "class": "BcelWeaver", "method": "weave", "filename": "BcelWeaver", "line": "1127"}, "caller": {"package": "org.aspectj.ajdt.internal.compiler", "class": "AjCompilerAdapter", "method": "weave", "filename": "AjCompilerAdapter", "line": "321"}}], "outer_pre": [], "outer_suf": [{"provider": {"package": "org.aspectj.weaver.bcel", "class": "BcelWeaver", "method": "weave", "filename": "BcelWeaver", "line": "1127"}, "caller": {"package": "org.aspectj.ajdt.internal.compiler", "class": "AjCompilerAdapter", "method": "weave", "filename": "AjCompilerAdapter", "line": "321"}}, {"provider": {"package": "org.aspectj.ajdt.internal.compiler", "class": "AjCompilerAdapter", "method": "afterCompiling", "filename": "AjCompilerAdapter", "line": "192"}, "caller": {"package": "org.aspectj.org.eclipse.jdt.internal.compiler", "class": "Compiler", "method": "compile", "filename": "Compiler", "line": "367"}}, {"provider": {"package": "org.aspectj.org.eclipse.jdt.internal.compiler", "class": "Compiler", "method": "compile", "filename": "Compiler", "line": "367"}, "caller": {"package": "org.aspectj.ajdt.internal.core.builder", "class": "AjBuildManager", "method": "performCompilation", "filename": "AjBuildManager", "line": "887"}}, {"provider": {"package": "org.aspectj.ajdt.internal.core.builder", "class": "AjBuildManager", "method": "batchBuild", "filename": "AjBuildManager", "line": "163"}, "caller": {"package": "org.aspectj.ajdt.ajc", "class": "AjdtCommand", "method": "doCommand", "filename": "AjdtCommand", "line": "112"}}, {"provider": {"package": "org.aspectj.ajdt.ajc", "class": "AjdtCommand", "method": "runCommand", "filename": "AjdtCommand", "line": "60"}, "caller": {"package": "org.aspectj.tools.ajc", "class": "Main", "method": "run", "filename": "Main", "line": "367"}}], "all": [{"provider": {"package": "org.aspectj.weaver.bcel", "class": "BcelShadow", "method": "prepareForMungers", "filename": "BcelShadow", "line": "284"}, "caller": {"package": "org.aspectj.weaver", "class": "Shadow", "method": "implement", "filename": "Shadow", "line": "470"}}, {"provider": {"package": "org.aspectj.weaver", "class": "Shadow", "method": "implement", "filename": "Shadow", "line": "470"}, "caller": {"package": "org.aspectj.weaver.bcel", "class": "BcelClassWeaver", "method": "implement", "filename": "BcelClassWeaver", "line": "2825"}}, {"provider": {"package": "org.aspectj.weaver.bcel", "class": "BcelWeaver", "method": "weave", "filename": "BcelWeaver", "line": "1127"}, "caller": {"package": "org.aspectj.ajdt.internal.compiler", "class": "AjCompilerAdapter", "method": "weave", "filename": "AjCompilerAdapter", "line": "321"}}, {"provider": {"package": "org.aspectj.ajdt.internal.compiler", "class": "AjCompilerAdapter", "method": "afterCompiling", "filename": "AjCompilerAdapter", "line": "192"}, "caller": {"package": "org.aspectj.org.eclipse.jdt.internal.compiler", "class": "Compiler", "method": "compile", "filename": "Compiler", "line": "367"}}, {"provider": {"package": "org.aspectj.org.eclipse.jdt.internal.compiler", "class": "Compiler", "method": "compile", "filename": "Compiler", "line": "367"}, "caller": {"package": "org.aspectj.ajdt.internal.core.builder", "class": "AjBuildManager", "method": "performCompilation", "filename": "AjBuildManager", "line": "887"}}, {"provider": {"package": "org.aspectj.ajdt.internal.core.builder", "class": "AjBuildManager", "method": "batchBuild", "filename": "AjBuildManager", "line": "163"}, "caller": {"package": "org.aspectj.ajdt.ajc", "class": "AjdtCommand", "method": "doCommand", "filename": "AjdtCommand", "line": "112"}}, {"provider": {"package": "org.aspectj.ajdt.ajc", "class": "AjdtCommand", "method": "runCommand", "filename": "AjdtCommand", "line": "60"}, "caller": {"package": "org.aspectj.tools.ajc", "class": "Main", "method": "run", "filename": "Main", "line": "367"}}]}, {"exception": "java.io.IOException", "inner": [], "outer_pre": [], "outer_suf": [], "all": []}, {"exception": "java.io.IOException", "inner": [], "outer_pre": [], "outer_suf": [], "all": []}, {"exception": "java.io.IOException", "inner": [], "outer_pre": [], "outer_suf": [], "all": []}, {"exception": "java.io.IOException", "inner": [], "outer_pre": [], "outer_suf": [], "all": []}, {"exception": "java.io.IOException", "inner": [], "outer_pre": [], "outer_suf": [], "all": []}, {"exception": "java.io.IOException", "inner": [{"provider": {"package": "org.aspectj.weaver.bcel", "class": "BcelShadow", "method": "prepareForMungers", "filename": "BcelShadow", "line": "284"}, "caller": {"package": "org.aspectj.weaver", "class": "Shadow", "method": "implement", "filename": "Shadow", "line": "470"}}, {"provider": {"package": "org.aspectj.weaver", "class": "Shadow", "method": "implement", "filename": "Shadow", "line": "470"}, "caller": {"package": "org.aspectj.weaver.bcel", "class": "BcelClassWeaver", "method": "implement", "filename": "BcelClassWeaver", "line": "2825"}}, {"provider": {"package": "org.aspectj.weaver.bcel", "class": "BcelWeaver", "method": "weave", "filename": "BcelWeaver", "line": "1127"}, "caller": {"package": "org.aspectj.ajdt.internal.compiler", "class": "AjCompilerAdapter", "method": "weave", "filename": "AjCompilerAdapter", "line": "321"}}], "outer_pre": [], "outer_suf": [{"provider": {"package": "org.aspectj.weaver.bcel", "class": "BcelWeaver", "method": "weave", "filename": "BcelWeaver", "line": "1127"}, "caller": {"package": "org.aspectj.ajdt.internal.compiler", "class": "AjCompilerAdapter", "method": "weave", "filename": "AjCompilerAdapter", "line": "321"}}, {"provider": {"package": "org.aspectj.ajdt.internal.compiler", "class": "AjCompilerAdapter", "method": "afterCompiling", "filename": "AjCompilerAdapter", "line": "192"}, "caller": {"package": "org.aspectj.org.eclipse.jdt.internal.compiler", "class": "Compiler", "method": "compile", "filename": "Compiler", "line": "367"}}, {"provider": {"package": "org.aspectj.org.eclipse.jdt.internal.compiler", "class": "Compiler", "method": "compile", "filename": "Compiler", "line": "367"}, "caller": {"package": "org.aspectj.ajdt.internal.core.builder", "class": "AjBuildManager", "method": "performCompilation", "filename": "AjBuildManager", "line": "887"}}, {"provider": {"package": "org.aspectj.ajdt.internal.core.builder", "class": "AjBuildManager", "method": "batchBuild", "filename": "AjBuildManager", "line": "163"}, "caller": {"package": "org.aspectj.ajdt.ajc", "class": "AjdtCommand", "method": "doCommand", "filename": "AjdtCommand", "line": "112"}}, {"provider": {"package": "org.aspectj.ajdt.ajc", "class": "AjdtCommand", "method": "runCommand", "filename": "AjdtCommand", "line": "60"}, "caller": {"package": "org.aspectj.tools.ajc", "class": "Main", "method": "run", "filename": "Main", "line": "367"}}], "all": [{"provider": {"package": "org.aspectj.weaver.bcel", "class": "BcelShadow", "method": "prepareForMungers", "filename": "BcelShadow", "line": "284"}, "caller": {"package": "org.aspectj.weaver", "class": "Shadow", "method": "implement", "filename": "Shadow", "line": "470"}}, {"provider": {"package": "org.aspectj.weaver", "class": "Shadow", "method": "implement", "filename": "Shadow", "line": "470"}, "caller": {"package": "org.aspectj.weaver.bcel", "class": "BcelClassWeaver", "method": "implement", "filename": "BcelClassWeaver", "line": "2825"}}, {"provider": {"package": "org.aspectj.weaver.bcel", "class": "BcelWeaver", "method": "weave", "filename": "BcelWeaver", "line": "1127"}, "caller": {"package": "org.aspectj.ajdt.internal.compiler", "class": "AjCompilerAdapter", "method": "weave", "filename": "AjCompilerAdapter", "line": "321"}}, {"provider": {"package": "org.aspectj.ajdt.internal.compiler", "class": "AjCompilerAdapter", "method": "afterCompiling", "filename": "AjCompilerAdapter", "line": "192"}, "caller": {"package": "org.aspectj.org.eclipse.jdt.internal.compiler", "class": "Compiler", "method": "compile", "filename": "Compiler", "line": "367"}}, {"provider": {"package": "org.aspectj.org.eclipse.jdt.internal.compiler", "class": "Compiler", "method": "compile", "filename": "Compiler", "line": "367"}, "caller": {"package": "org.aspectj.ajdt.internal.core.builder", "class": "AjBuildManager", "method": "performCompilation", "filename": "AjBuildManager", "line": "887"}}, {"provider": {"package": "org.aspectj.ajdt.internal.core.builder", "class": "AjBuildManager", "method": "batchBuild", "filename": "AjBuildManager", "line": "163"}, "caller": {"package": "org.aspectj.ajdt.ajc", "class": "AjdtCommand", "method": "doCommand", "filename": "AjdtCommand", "line": "112"}}, {"provider": {"package": "org.aspectj.ajdt.ajc", "class": "AjdtCommand", "method": "runCommand", "filename": "AjdtCommand", "line": "60"}, "caller": {"package": "org.aspectj.tools.ajc", "class": "Main", "method": "run", "filename": "Main", "line": "367"}}]}]