[{"inner": [{"provider": {"package": "org.eclipse.ui.internal.handlers", "class": "LegacyHandlerService", "method": "executeCommand", "filename": "LegacyHandlerService", "line": "343"}, "caller": {"package": "org.eclipse.ui.internal.quickaccess", "class": "CommandElement", "method": "execute", "filename": "CommandElement", "line": "72"}}, {"provider": {"package": "org.eclipse.ui.internal.quickaccess", "class": "QuickAccessContents$1", "method": "keyPressed", "filename": "QuickAccessContents", "line": "495"}, "caller": {"package": "org.eclipse.swt.widgets", "class": "TypedListener", "method": "handleEvent", "filename": "TypedListener", "line": "167"}}, {"provider": {"package": "org.eclipse.swt.widgets", "class": "Display", "method": "windowProc", "filename": "Display", "line": "5784"}, "caller": {"package": "org.eclipse.swt.internal.cocoa", "class": "OS", "method": "objc_msgSendSuper", "filename": "OS", "line": "-2"}}, {"provider": {"package": "org.eclipse.swt.internal.cocoa", "class": "OS", "method": "objc_msgSendSuper", "filename": "OS", "line": "-2"}, "caller": {"package": "org.eclipse.swt.widgets", "class": "Widget", "method": "callSuper", "filename": "Widget", "line": "227"}}, {"provider": {"package": "org.eclipse.swt.widgets", "class": "Display", "method": "windowProc", "filename": "Display", "line": "5694"}, "caller": {"package": "org.eclipse.swt.internal.cocoa", "class": "OS", "method": "objc_msgSendSuper", "filename": "OS", "line": "-2"}}, {"provider": {"package": "org.eclipse.swt.internal.cocoa", "class": "OS", "method": "objc_msgSendSuper", "filename": "OS", "line": "-2"}, "caller": {"package": "org.eclipse.swt.widgets", "class": "Widget", "method": "callSuper", "filename": "Widget", "line": "227"}}, {"provider": {"package": "org.eclipse.swt.widgets", "class": "Display", "method": "windowProc", "filename": "Display", "line": "5756"}, "caller": {"package": "org.eclipse.swt.internal.cocoa", "class": "OS", "method": "objc_msgSendSuper", "filename": "OS", "line": "-2"}}, {"provider": {"package": "org.eclipse.swt.internal.cocoa", "class": "OS", "method": "objc_msgSendSuper", "filename": "OS", "line": "-2"}, "caller": {"package": "org.eclipse.swt.widgets", "class": "Display", "method": "applicationSendEvent", "filename": "Display", "line": "5193"}}], "outer_pre": [{"provider": {"package": "org.eclipse.oomph.setup.ui.wizards", "class": "SetupWizard", "method": "canFinish", "filename": "SetupWizard", "line": "432"}, "caller": {"package": "org.eclipse.jface.wizard", "class": "WizardDialog", "method": "updateButtons", "filename": "WizardDialog", "line": "1314"}}, {"provider": {"package": "org.eclipse.jface.wizard", "class": "WizardDialog$8", "method": "run", "filename": "WizardDialog", "line": "1197"}, "caller": {"package": "org.eclipse.swt.custom", "class": "BusyIndicator", "method": "showWhile", "filename": "BusyIndicator", "line": "70"}}, {"provider": {"package": "org.eclipse.swt.custom", "class": "BusyIndicator", "method": "showWhile", "filename": "BusyIndicator", "line": "70"}, "caller": {"package": "org.eclipse.jface.wizard", "class": "WizardDialog", "method": "showPage", "filename": "WizardDialog", "line": "1194"}}, {"provider": {"package": "org.eclipse.jface.wizard", "class": "WizardDialog", "method": "buttonPressed", "filename": "WizardDialog", "line": "425"}, "caller": {"package": "org.eclipse.jface.dialogs", "class": "Dialog$2", "method": "widgetSelected", "filename": "Dialog", "line": "619"}}, {"provider": {"package": "org.eclipse.jface.dialogs", "class": "Dialog$2", "method": "widgetSelected", "filename": "Dialog", "line": "619"}, "caller": {"package": "org.eclipse.swt.widgets", "class": "TypedListener", "method": "handleEvent", "filename": "TypedListener", "line": "248"}}, {"provider": {"package": "org.eclipse.swt.widgets", "class": "Display", "method": "readAndDispatch", "filename": "Display", "line": "3698"}, "caller": {"package": "org.eclipse.jface.window", "class": "Window", "method": "runEventLoop", "filename": "Window", "line": "827"}}, {"provider": {"package": "org.eclipse.jface.window", "class": "Window", "method": "open", "filename": "Window", "line": "803"}, "caller": {"package": "org.eclipse.ui.internal.handlers", "class": "WizardHandler$Import", "method": "executeHandler", "filename": "WizardHandler", "line": "158"}}, {"provider": {"package": "org.eclipse.ui.internal.handlers", "class": "E4HandlerProxy", "method": "execute", "filename": "E4HandlerProxy", "line": "90"}, "caller": {"package": "sun.reflect", "class": "NativeMethodAccessorImpl", "method": "invoke0", "filename": "NativeMethodAccessorImpl", "line": "-2"}}, {"provider": {"package": "sun.reflect", "class": "DelegatingMethodAccessorImpl", "method": "invoke", "filename": "DelegatingMethodAccessorImpl", "line": "43"}, "caller": {"package": "java.lang.reflect", "class": "Method", "method": "invoke", "filename": "Method", "line": "497"}}, {"provider": {"package": "java.lang.reflect", "class": "Method", "method": "invoke", "filename": "Method", "line": "497"}, "caller": {"package": "org.eclipse.e4.core.internal.di", "class": "MethodRequestor", "method": "execute", "filename": "MethodRequestor", "line": "56"}}, {"provider": {"package": "org.eclipse.e4.core.internal.di", "class": "InjectorImpl", "method": "invoke", "filename": "InjectorImpl", "line": "234"}, "caller": {"package": "org.eclipse.e4.core.contexts", "class": "ContextInjectionFactory", "method": "invoke", "filename": "ContextInjectionFactory", "line": "132"}}, {"provider": {"package": "org.eclipse.e4.core.contexts", "class": "ContextInjectionFactory", "method": "invoke", "filename": "ContextInjectionFactory", "line": "132"}, "caller": {"package": "org.eclipse.e4.core.commands.internal", "class": "HandlerServiceHandler", "method": "execute", "filename": "HandlerServiceHandler", "line": "152"}}, {"provider": {"package": "org.eclipse.e4.core.commands.internal", "class": "HandlerServiceHandler", "method": "execute", "filename": "HandlerServiceHandler", "line": "152"}, "caller": {"package": "org.eclipse.core.commands", "class": "Command", "method": "executeWithChecks", "filename": "Command", "line": "493"}}, {"provider": {"package": "org.eclipse.core.commands", "class": "ParameterizedCommand", "method": "executeWithChecks", "filename": "ParameterizedCommand", "line": "486"}, "caller": {"package": "org.eclipse.e4.core.commands.internal", "class": "HandlerServiceImpl", "method": "executeHandler", "filename": "HandlerServiceImpl", "line": "210"}}, {"provider": {"package": "org.eclipse.e4.core.commands.internal", "class": "HandlerServiceImpl", "method": "executeHandler", "filename": "HandlerServiceImpl", "line": "210"}, "caller": {"package": "org.eclipse.ui.internal.handlers", "class": "LegacyHandlerService", "method": "executeCommand", "filename": "LegacyHandlerService", "line": "343"}}, {"provider": {"package": "org.eclipse.ui.internal.handlers", "class": "LegacyHandlerService", "method": "executeCommand", "filename": "LegacyHandlerService", "line": "343"}, "caller": {"package": "org.eclipse.ui.internal.quickaccess", "class": "CommandElement", "method": "execute", "filename": "CommandElement", "line": "72"}}], "outer_suf": [], "all": [{"provider": {"package": "org.eclipse.oomph.setup.ui.wizards", "class": "SetupWizard", "method": "canFinish", "filename": "SetupWizard", "line": "432"}, "caller": {"package": "org.eclipse.jface.wizard", "class": "WizardDialog", "method": "updateButtons", "filename": "WizardDialog", "line": "1314"}}]}]