[{"exception": "exception", "inner": [{"provider": {"package": "eu.geclipse.core.filesystem.internal.filesystem", "class": "GEclipseFileStore", "method": "getChild", "filename": "GEclipseFileStore", "line": "168"}, "caller": {"package": "org.eclipse.core.filesystem.provider", "class": "FileStore", "method": "getChild", "filename": "FileStore", "line": "296"}}, {"provider": {"package": "org.eclipse.core.filesystem.provider", "class": "FileStore", "method": "getChild", "filename": "FileStore", "line": "296"}, "caller": {"package": "org.eclipse.core.internal.localstore", "class": "FileStoreRoot", "method": "createStore", "filename": "FileStoreRoot", "line": "93"}}, {"provider": {"package": "org.eclipse.core.internal.localstore", "class": "FileSystemResourceManager", "method": "getStore", "filename": "FileSystemResourceManager", "line": "355"}, "caller": {"package": "org.eclipse.core.internal.resources", "class": "Resource", "method": "getStore", "filename": "Resource", "line": "1085"}}, {"provider": {"package": "org.eclipse.core.internal.resources", "class": "Resource", "method": "getStore", "filename": "Resource", "line": "1085"}, "caller": {"package": "org.eclipse.core.internal.localstore", "class": "FileSystemResourceManager", "method": "refreshResource", "filename": "FileSystemResourceManager", "line": "726"}}, {"provider": {"package": "org.eclipse.core.internal.localstore", "class": "FileSystemResourceManager", "method": "refresh", "filename": "FileSystemResourceManager", "line": "714"}, "caller": {"package": "org.eclipse.core.internal.resources", "class": "Resource", "method": "refreshLocal", "filename": "Resource", "line": "1420"}}, {"provider": {"package": "org.eclipse.core.internal.resources", "class": "Resource", "method": "refreshLocal", "filename": "Resource", "line": "1420"}, "caller": {"package": "org.eclipse.core.internal.refresh", "class": "RefreshJob", "method": "runInWorkspace", "filename": "RefreshJob", "line": "141"}}, {"provider": {"package": "org.eclipse.core.internal.refresh", "class": "RefreshJob", "method": "runInWorkspace", "filename": "RefreshJob", "line": "141"}, "caller": {"package": "org.eclipse.core.internal.resources", "class": "InternalWorkspaceJob", "method": "run", "filename": "InternalWorkspaceJob", "line": "38"}}, {"provider": {"package": "org.eclipse.core.internal.resources", "class": "InternalWorkspaceJob", "method": "run", "filename": "InternalWorkspaceJob", "line": "38"}, "caller": {"package": "org.eclipse.core.internal.jobs", "class": "Worker", "method": "run", "filename": "Worker", "line": "55"}}], "outer_pre": [{"provider": {"package": "org.eclipse.core.runtime", "class": "Assert", "method": "isTrue", "filename": "Assert", "line": "109"}, "caller": {"package": "eu.geclipse.efs.gridftp", "class": "GridFile", "method": "getChild", "filename": "GridFile", "line": "154"}}, {"provider": {"package": "eu.geclipse.efs.gridftp", "class": "GridFile", "method": "getChild", "filename": "GridFile", "line": "154"}, "caller": {"package": "eu.geclipse.core.filesystem.internal.filesystem", "class": "GEclipseFileStore", "method": "getChild", "filename": "GEclipseFileStore", "line": "168"}}, {"provider": {"package": "eu.geclipse.core.filesystem.internal.filesystem", "class": "GEclipseFileStore", "method": "getChild", "filename": "GEclipseFileStore", "line": "168"}, "caller": {"package": "org.eclipse.core.filesystem.provider", "class": "FileStore", "method": "getChild", "filename": "FileStore", "line": "296"}}, {"provider": {"package": "org.eclipse.core.filesystem.provider", "class": "FileStore", "method": "getChild", "filename": "FileStore", "line": "296"}, "caller": {"package": "org.eclipse.core.internal.localstore", "class": "FileStoreRoot", "method": "createStore", "filename": "FileStoreRoot", "line": "93"}}], "outer_suf": [], "all": [{"provider": {"package": "org.eclipse.core.runtime", "class": "Assert", "method": "isTrue", "filename": "Assert", "line": "109"}, "caller": {"package": "eu.geclipse.efs.gridftp", "class": "GridFile", "method": "getChild", "filename": "GridFile", "line": "154"}}, {"provider": {"package": "eu.geclipse.efs.gridftp", "class": "GridFile", "method": "getChild", "filename": "GridFile", "line": "154"}, "caller": {"package": "eu.geclipse.core.filesystem.internal.filesystem", "class": "GEclipseFileStore", "method": "getChild", "filename": "GEclipseFileStore", "line": "168"}}]}]