{"stack_id": 355927, "component": "Hudson Connector", "importance": "P3 normal      with      1       vote", "reported_time": "2011-08-26 05:29", "modified_time": "2018-07-06 03:20", "stack_arr": [{"exception": "error", "calls": [{"package": "org.eclipse.mylyn.internal.hudson.core", "class": "HudsonCorePlugin", "method": "toCoreException", "filename": "HudsonCorePlugin", "line": "61"}, {"package": "org.eclipse.mylyn.internal.hudson.core", "class": "HudsonServerBehaviour", "method": "runBuild", "filename": "HudsonServerBehaviour", "line": "738"}, {"package": "org.eclipse.mylyn.builds.internal.core.operations", "class": "RunBuildOperation$1", "method": "doExecute", "filename": "RunBuildOperation", "line": "55"}, {"package": "org.eclipse.mylyn.builds.internal.core.operations", "class": "BuildJob", "method": "run", "filename": "BuildJob", "line": "79"}, {"package": "org.eclipse.core.internal.jobs", "class": "Worker", "method": "run", "filename": "Worker", "line": "54"}]}, {"exception": "org.eclipse.mylyn.internal.hudson.core.client.HudsonException", "calls": [{"package": "org.eclipse.mylyn.internal.hudson.core.client", "class": "HudsonOperation", "method": "run", "filename": "HudsonOperation", "line": "34"}, {"package": "org.eclipse.mylyn.internal.hudson.core.client", "class": "RestfulHudsonClient", "method": "runBuild", "filename": "RestfulHudsonClient", "line": "397"}, {"package": "org.eclipse.mylyn.internal.hudson.core", "class": "HudsonServerBehaviour", "method": "runBuild", "filename": "HudsonServerBehaviour", "line": "736"}]}, {"exception": "java.io.IOException", "calls": [{"package": "org.eclipse.mylyn.commons.http", "class": "CommonHttpClient", "method": "needsReauthentication", "filename": "CommonHttpClient", "line": "105"}, {"package": "org.eclipse.mylyn.commons.http", "class": "HttpOperation", "method": "needsReauthentication", "filename": "HttpOperation", "line": "102"}, {"package": "org.eclipse.mylyn.commons.http", "class": "HttpOperation", "method": "execute", "filename": "HttpOperation", "line": "76"}, {"package": "org.eclipse.mylyn.internal.hudson.core.client", "class": "RestfulHudsonClient$7", "method": "execute", "filename": "RestfulHudsonClient", "line": "390"}, {"package": "org.eclipse.mylyn.internal.hudson.core.client", "class": "HudsonOperation", "method": "run", "filename": "HudsonOperation", "line": "32"}, {"package": "org.eclipse.mylyn.internal.commons.repositories", "class": "LocationService", "method": "requestCredentials", "filename": "LocationService", "line": "93"}, {"package": "org.eclipse.mylyn.builds.internal.core.util", "class": "RepositoryWebLocation", "method": "requestCredentials", "filename": "RepositoryWebLocation", "line": "55"}, {"package": "org.eclipse.mylyn.commons.http", "class": "CommonHttpClient", "method": "needsReauthentication", "filename": "CommonHttpClient", "line": "99"}]}], "duplicated_stack_id": ["341414"]}